qmult.v
module qmult #(
	//Parameterized values
	parameter Q = 16,
	parameter N = 32
	)
	(
	 input	signed	[N-1:0]	i_multiplicand,
	 input	signed	[N-1:0]	i_multiplier,
	 output	signed	[N-1:0]	o_result,
	 output	reg	ovr
	 );
	 
	wire signed [2*N-1:0]	r_result;//Nhan 2 so cos gia tri N bit thi can 1 thanh ghi co do rong la N+N = 2N 
	reg signed [N-1:0]	r_RetVal;

	wire signed [N-1:0] temp_multiplicand, temp_meltiplier;
	reg signed  [N-1:0] temp_RetVal;
	reg is_signed;

	//--------------------------------------------------------------------------------
	assign o_result = r_RetVal;	//	Chi lay ket qua co cung so bit theo cau truc cua fixed point

	//---------------------------------------------------------------------------------
	//always @(i_multiplicand, i_multiplier) begin//Thuc hien nhan bat cu khi nao input thay doi
	// Thuc hien kiem tra bit dau
	assign temp_multiplicand = i_multiplicand[N-1] ? -i_multiplicand : i_multiplicand;
	assign temp_meltiplier = i_multiplier[N-1] ? -i_multiplier : i_multiplier;
	assign r_result = temp_meltiplier * temp_multiplicand;
	//end

	always @(r_result) begin//Bat cu khi nao ket qua thay doi thi thuc hien
		is_signed = i_multiplicand[N-1] ^ i_multiplier[N-1];	// Kiem tra bit co dau
		temp_RetVal[N-2:0] = r_result[N-2+Q:Q];			// Bo N/2 bit dau vaf N/2 bit cuoi
		temp_RetVal[N-1] = 0;					// so khong cos dau
		r_RetVal = is_signed ? -temp_RetVal : temp_RetVal;
		
		ovr = |r_result[2*N-2:N-1+Q];// Neu N/2 bit dau >0 thi phep toan tran
	end

endmodule

Dh_cal.v
/*
* Module: Dh_cal (Corrected Version 2)
* Chức năng: Tự động tích lũy 8 giá trị |Hq|^2 và tự clear.
* - Xử lý Dh_en là xung đơn.
* - Dh_clear là tín hiệu nội bộ, tự động.
* - Tích lũy ngay lập tức vì qmult là tổ hợp.
*/

module Dh_cal #(
    parameter Q = 8,
    parameter N = 16
)
(
    input clk,
    input rst,
    // Dh_clear đã được loại bỏ, module sẽ tự động clear
    input Dh_en, // Tín hiệu xung đơn báo hiệu dữ liệu (in_real, in_im) hợp lệ
    input signed [N-1:0] in_real,
    input signed [N-1:0] in_im,

    output reg signed [N-1:0] Dh_out,
    output reg Dh_result_valid
);
    // Độ rộng thanh ghi tích lũy đủ lớn để tránh tràn số
    localparam ACC_WIDTH = 2*N + 3; // 32 + log2(8) = 35 bits

    // Các tín hiệu trung gian
    wire signed [N-1:0] product_r, product_i;
    wire ovr_multr, ovr_multi;
    wire signed [N:0] SoP; // Sum of Products (|Hq|^2 cho một phần tử)

    reg [2:0] dh_count; // Đếm từ 0 đến 7
    reg signed [ACC_WIDTH-1:0] dh_reg;
    
    // Tín hiệu nội bộ để tự động clear
    wire internal_clear;

    // --- Khối nhân tổ hợp ---
    qmult #(.Q(Q), .N(N)) qmult_real (
        .i_multiplicand(in_real),
        .i_multiplier(in_real),
        .o_result(product_r),
        .ovr(ovr_multr)
    );

    qmult #(.Q(Q), .N(N)) qmult_im (
        .i_multiplicand(in_im),
        .i_multiplier(in_im),
        .o_result(product_i),
        .ovr(ovr_multi)
    );

    // Tính |Hq|^2 = real^2 + imag^2
    assign SoP = product_r + product_i;
    
    // --- Logic Tích Lũy và Đếm ---
    // Tự động clear khi reset hoặc khi tính xong kết quả
    assign internal_clear = Dh_result_valid;

    always @(posedge clk or posedge rst) begin
        if (rst) begin
            dh_reg <= 0;
            dh_count <= 0;
        end else if (internal_clear) begin
            dh_reg <= 0;
            dh_count <= 0;
        end else if (Dh_en) begin
            // Tích lũy ngay khi có Dh_en, vì SoP là tổ hợp
            dh_reg <= dh_reg + {{ACC_WIDTH-N-1{SoP[N]}}, SoP};
            dh_count <= dh_count + 1;
        end
    end

    // --- Logic Xuất Kết Quả ---
    always @(posedge clk or posedge rst) begin
        if (rst) begin
            Dh_result_valid <= 1'b0;
            Dh_out <= 0;
        end else begin
            // Báo valid khi nhận đủ 8 giá trị (đếm từ 0 đến 7)
            if ((dh_count == 3'd7)&& Dh_en) begin
                Dh_result_valid <= 1'b1;
                // Kết quả cuối cùng là giá trị tích lũy hiện tại CỘNG với giá trị SoP cuối cùng
                Dh_out <= (dh_reg + {{ACC_WIDTH-N-1{SoP[N]}}, SoP});
            end else begin
                Dh_result_valid <= 1'b0;
            end
        end
    end

endmodule

tb_Dh_cal.sv
`timescale 1ns/1ps

module tb_Dh_cal;

    // --- Các tham số ---
    parameter Q = 8;
    parameter N = 16;
    parameter CLK_PERIOD = 10;
    
    // Kích thước ma trận Hq đầu vào là 4x32
    parameter HQ_ROWS = 4;
    parameter HQ_COLS = 32; 

    // Tên file stimulus
    parameter HQ_REAL_FILE = "Hq_real_gold_Q8_8.hex";
    parameter HQ_IMAG_FILE = "Hq_imag_gold_Q8_8.hex";

    // --- Tín hiệu Testbench ---
    reg clk;
    reg rst;
    reg Dh_en;
    reg signed [N-1:0] in_real;
    reg signed [N-1:0] in_im;

    wire signed [N-1:0] Dh_out;
    wire Dh_result_valid;

    // --- Bộ nhớ để lưu trữ toàn bộ dữ liệu Hq đọc từ file ---
    reg signed [N-1:0] hq_stim_r [0:HQ_ROWS-1][0:HQ_COLS-1];
    reg signed [N-1:0] hq_stim_i [0:HQ_ROWS-1][0:HQ_COLS-1];

    // --- Khởi tạo DUT (Device Under Test) ---
    // Đảm bảo bạn đang dùng phiên bản Dh_cal đã được sửa lỗi logic tích lũy
    Dh_cal #(.Q(Q), .N(N)) dut (
        .clk(clk),
        .rst(rst),
        .Dh_en(Dh_en),
        .in_real(in_real),
        .in_im(in_im),
        .Dh_out(Dh_out),
        .Dh_result_valid(Dh_result_valid)
    );

    // --- Logic Testbench ---

    // Tạo clock
    always #(CLK_PERIOD/2) clk = ~clk;

    // Luồng test chính (Test Sequencer)
    initial begin
        $dumpfile("tb_dh_cal.vcd");
        $dumpvars(0, tb_Dh_cal);
        
        // 1. Khởi tạo và Reset
        clk = 0;
        initialize_signals();
        reset_dut();

        // 2. Nạp toàn bộ dữ liệu Hq từ file vào bộ nhớ (chỉ một lần)
        read_hq_files();
        
        // 3. Chạy các test case tuần tự
        run_one_dh_calculation(0); // Test cho Dh_0

        @(posedge clk); // Chờ một chút giữa các lần test

        run_one_dh_calculation(1); // Test cho Dh_1

        @(posedge clk);

        run_one_dh_calculation(2); // Test cho Dh_2

        $display("\n--- Test Sequence Finished ---");
        $finish;
    end

    // --- Các Task Cho Testbench ---

    task initialize_signals;
    begin
        Dh_en = 0;
        in_real = 0;
        in_im = 0;
    end
    endtask

    task reset_dut;
    begin
        rst = 1;
        #(2 * CLK_PERIOD);
        rst = 0;
        #(2 * CLK_PERIOD);
    end
    endtask

    // Task đọc toàn bộ 2 file Hq vào 2 mảng 2D
    task read_hq_files;
        integer fd_real, fd_imag, dummy;
        reg signed [N-1:0] temp_data;
        integer i, j;
    begin
        fd_real = $fopen(HQ_REAL_FILE, "r");
        fd_imag = $fopen(HQ_IMAG_FILE, "r");
        
        if (fd_real == 0 || fd_imag == 0) begin
            $display("ERROR: Could not open one or both Hq stimulus files.");
            $finish;
        end

        // Vòng lặp 1: Đọc toàn bộ file real
        $display("Reading REAL stimulus file...");
        for (j = 0; j < HQ_COLS; j = j + 1) begin
            for (i = 0; i < HQ_ROWS; i = i + 1) begin
                dummy = $fscanf(fd_real, "%h", temp_data);
                hq_stim_r[i][j] = temp_data;
            end
        end
        $fclose(fd_real);

        // Vòng lặp 2: Đọc toàn bộ file imag
        $display("Reading IMAGINARY stimulus file...");
        for (j = 0; j < HQ_COLS; j = j + 1) begin
            for (i = 0; i < HQ_ROWS; i = i + 1) begin
                dummy = $fscanf(fd_imag, "%h", temp_data);
                hq_stim_i[i][j] = temp_data;
            end
        end
        $fclose(fd_imag);
        
        $display("Finished reading all Hq stimulus files into memory.");
    end
    endtask

    // Task thực thi một phép tính Dh hoàn chỉnh cho một q_index
    // ĐÃ CẬP NHẬT LOGIC CHÍNH XÁC
    task run_one_dh_calculation;
        input [3:0] q_idx; // Chỉ số của Dh cần tính (0 đến 15)
        integer i;
        integer col1_idx, col2_idx;
    begin
        $display("\n--- Running Test for Dh_%0d ---", q_idx);

        // 2. Tính toán chỉ số các cột cần lấy dữ liệu theo đúng thuật toán
        col1_idx = q_idx * 2;
        col2_idx = q_idx * 2 + 1;

        // 3. Nạp 8 giá trị Hq cần thiết để tính Dh
        //    Gồm 4 giá trị từ cột 2*q và 4 giá trị từ cột 2*q + 1
        
        $display("Feeding Hq column %0d data...", col1_idx);
        for (i = 0; i < HQ_ROWS; i = i + 1) begin
            Dh_en = 1;
            in_real = hq_stim_r[i][col1_idx];
            in_im = hq_stim_i[i][col1_idx];
            @(posedge clk);
	    Dh_en = 0;
        end
        
        $display("Feeding Hq column %0d data...", col2_idx);
        for (i = 0; i < HQ_ROWS; i = i + 1) begin
            Dh_en = 1;
            in_real = hq_stim_r[i][col2_idx];
            in_im = hq_stim_i[i][col2_idx];
            @(posedge clk);
	    Dh_en = 0;
        end
        //Dh_en = 0;

        // 4. Chờ cho đến khi DUT báo kết quả hợp lệ
        $display("Waiting for DUT result...");
        wait(Dh_result_valid);
        
        // 5. In kết quả từ DUT ra màn hình để bạn quan sát
        $display(">>> DUT Result for Dh_%0d = %h (%f)", q_idx, Dh_out, $signed(Dh_out)/256.0);
        
        // Chờ một chu kỳ để các tín hiệu ổn định trước khi bắt đầu test case mới
        @(posedge clk);
    end
    endtask

endmodule

tb_dh_cal.vcd
$date
	Mon Oct  6 21:45:36 2025
$end
$version
	Icarus Verilog
$end
$timescale
	1ps
$end
$scope module tb_Dh_cal $end
$var wire 1 ! Dh_result_valid $end
$var wire 16 " Dh_out [15:0] $end
$var reg 1 # Dh_en $end
$var reg 1 $ clk $end
$var reg 16 % in_im [15:0] $end
$var reg 16 & in_real [15:0] $end
$var reg 1 ' rst $end
$scope module dut $end
$var wire 1 # Dh_en $end
$var wire 1 $ clk $end
$var wire 16 ( in_im [15:0] $end
$var wire 16 ) in_real [15:0] $end
$var wire 1 * internal_clear $end
$var wire 1 ' rst $end
$var wire 16 + product_r [15:0] $end
$var wire 16 , product_i [15:0] $end
$var wire 1 - ovr_multr $end
$var wire 1 . ovr_multi $end
$var wire 17 / SoP [16:0] $end
$var reg 16 0 Dh_out [15:0] $end
$var reg 1 ! Dh_result_valid $end
$var reg 3 1 dh_count [2:0] $end
$var reg 35 2 dh_reg [34:0] $end
$scope module qmult_im $end
$var wire 16 3 i_multiplicand [15:0] $end
$var wire 16 4 i_multiplier [15:0] $end
$var wire 16 5 temp_multiplicand [15:0] $end
$var wire 16 6 temp_meltiplier [15:0] $end
$var wire 32 7 r_result [31:0] $end
$var wire 16 8 o_result [15:0] $end
$var reg 1 9 is_signed $end
$var reg 1 . ovr $end
$var reg 16 : r_RetVal [15:0] $end
$var reg 16 ; temp_RetVal [15:0] $end
$upscope $end
$scope module qmult_real $end
$var wire 16 < i_multiplicand [15:0] $end
$var wire 16 = i_multiplier [15:0] $end
$var wire 16 > temp_multiplicand [15:0] $end
$var wire 16 ? temp_meltiplier [15:0] $end
$var wire 32 @ r_result [31:0] $end
$var wire 16 A o_result [15:0] $end
$var reg 1 B is_signed $end
$var reg 1 - ovr $end
$var reg 16 C r_RetVal [15:0] $end
$var reg 16 D temp_RetVal [15:0] $end
$upscope $end
$upscope $end
$scope task initialize_signals $end
$upscope $end
$scope task read_hq_files $end
$var reg 16 E temp_data [15:0] $end
$var integer 32 F dummy [31:0] $end
$var integer 32 G fd_imag [31:0] $end
$var integer 32 H fd_real [31:0] $end
$var integer 32 I i [31:0] $end
$var integer 32 J j [31:0] $end
$upscope $end
$scope task reset_dut $end
$upscope $end
$scope task run_one_dh_calculation $end
$var reg 4 K q_idx [3:0] $end
$var integer 32 L col1_idx [31:0] $end
$var integer 32 M col2_idx [31:0] $end
$var integer 32 N i [31:0] $end
$upscope $end
$upscope $end
$enddefinitions $end
#0
$dumpvars
bx N
bx M
bx L
bx K
bx J
bx I
bx H
bx G
bx F
bx E
b0 D
b0 C
0B
b0 A
b0 @
b0 ?
b0 >
b0 =
b0 <
b0 ;
b0 :
09
b0 8
b0 7
b0 6
b0 5
b0 4
b0 3
b0 2
b0 1
b0 0
b0 /
0.
0-
b0 ,
b0 +
0*
b0 )
b0 (
1'
b0 &
b0 %
0$
0#
b0 "
0!
$end
#5000
1$
#10000
0$
#15000
1$
#20000
0$
0'
#25000
1$
#30000
0$
#35000
1$
#40000
b110110 ,
b110110 8
b110110 :
b110110 ;
0-
b110110 /
b0 +
b0 A
b0 C
b0 D
b11011001100100 7
b1110110 5
b1110110 6
b10101001 @
b1101 >
b1101 ?
0$
b1110110 %
b1110110 (
b1110110 3
b1110110 4
b1111111111110011 &
b1111111111110011 )
b1111111111110011 <
b1111111111110011 =
1#
b0 N
b1 M
b0 L
b0 K
b1 F
b100000001 E
b100 I
b100000 J
b10000000000000000000000000000100 G
b10000000000000000000000000000011 H
#45000
b1 1
b110110 2
b1001101 ,
b1001101 8
b1001101 :
b1001101 ;
b1010010 /
b101 +
b101 A
b101 C
b101 D
b10001101 5
b100110110101001 7
b10001101 6
b100110 >
b10110100100 @
b100110 ?
b1111111101110011 %
b1111111101110011 (
b1111111101110011 3
b1111111101110011 4
b1111111111011010 &
b1111111111011010 )
b1111111111011010 <
b1111111111011010 =
b1 N
1#
1$
#50000
0$
#55000
b10 1
b10001000 2
b111001 ,
b111001 8
b111001 :
b111001 ;
b1010111 /
b11110 +
b11110 A
b11110 C
b11110 D
b1111001 5
b11100100110001 7
b1111001 6
b1011000 >
b1111001000000 @
b1011000 ?
b1111111110000111 %
b1111111110000111 (
b1111111110000111 3
b1111111110000111 4
b1111111110101000 &
b1111111110101000 )
b1111111110101000 <
b1111111110101000 =
b10 N
1#
1$
#60000
0$
#65000
b11 1
b11011111 2
b0 ,
b0 8
b0 :
b0 ;
b111001 /
b111001 +
b111001 A
b111001 C
b111001 D
b1000 5
b1000000 7
b1000 6
b1111001 >
b11100100110001 @
b1111001 ?
b1000 %
b1000 (
b1000 3
b1000 4
b1111111110000111 &
b1111111110000111 )
b1111111110000111 <
b1111111110000111 =
b11 N
1#
1$
#70000
0$
#75000
b100 1
b100011000 2
b1111 ,
b1111 8
b1111 :
b1111 ;
b11001 /
b1010 +
b1010 A
b1010 C
b1010 D
b111110 5
b111100000100 7
b111110 6
b110011 >
b101000101001 @
b110011 ?
b1111111111000010 %
b1111111111000010 (
b1111111111000010 3
b1111111111000010 4
b110011 &
b110011 )
b110011 <
b110011 =
b0 N
1#
1$
#80000
0$
#85000
b101 1
b100110001 2
b11 ,
b11 8
b11 :
b11 ;
b100 /
b1 +
b1 A
b1 C
b1 D
b11101 5
b1101001001 7
b11101 6
b10001 >
b100100001 @
b10001 ?
b11101 %
b11101 (
b11101 3
b11101 4
b1111111111101111 &
b1111111111101111 )
b1111111111101111 <
b1111111111101111 =
b1 N
1#
1$
#90000
0$
#95000
b110 1
b100110101 2
b110010111 ,
b110010111 8
b110010111 :
b110010111 ;
b111110111 /
b1100000 +
b1100000 A
b1100000 C
b1100000 D
b101000011 5
b11001011110001001 7
b101000011 6
b10011101 >
b110000001001001 @
b10011101 ?
b1111111010111101 %
b1111111010111101 (
b1111111010111101 3
b1111111010111101 4
b10011101 &
b10011101 )
b10011101 <
b10011101 =
b10 N
1#
1$
#100000
0$
#105000
b111 1
b1100101100 2
b1110111 ,
b1110111 8
b1110111 :
b1110111 ;
b1111100100 /
b1101101101 +
b1101101101 A
b1101101101 C
b1101101101 D
b10101111 5
b111011110100001 7
b10101111 6
b111011010 >
b110110110110100100 @
b111011010 ?
b10101111 %
b10101111 (
b10101111 3
b10101111 4
b1111111000100110 &
b1111111000100110 )
b1111111000100110 <
b1111111000100110 =
b11 N
1#
1$
#110000
0$
#115000
b11100010000 "
b11100010000 0
1*
1!
b100 N
0#
1$
#120000
0$
#125000
b0 1
b0 2
1$
#130000
0$
#135000
0*
0!
b110001 ,
b110001 8
b110001 :
b110001 ;
b1000111 /
b10110 +
b10110 A
b10110 C
b10110 D
b1110000 5
b11000100000000 7
b1110000 6
b1001100 >
b1011010010000 @
b1001100 ?
b1111111110010000 %
b1111111110010000 (
b1111111110010000 3
b1111111110010000 4
b1001100 &
b1001100 )
b1001100 <
b1001100 =
1#
b0 N
b11 M
b10 L
b1 K
1$
#140000
0$
#145000
b1 1
b1000111 2
b100 ,
b100 8
b100 :
b100 ;
b1000110 /
b1000010 +
b1000010 A
b1000010 C
b1000010 D
b100010 5
b10010000100 7
b100010 6
b10000010 >
b100001000000100 @
b10000010 ?
b1111111111011110 %
b1111111111011110 (
b1111111111011110 3
b1111111111011110 4
b1111111101111110 &
b1111111101111110 )
b1111111101111110 <
b1111111101111110 =
b1 N
1#
1$
#150000
0$
#155000
b10 1
b10001101 2
b1001001 ,
b1001001 8
b1001001 :
b1001001 ;
b1011101 /
b10100 +
b10100 A
b10100 C
b10100 D
b10001001 5
b100100101010001 7
b10001001 6
b1001000 >
b1010001000000 @
b1001000 ?
b1111111101110111 %
b1111111101110111 (
b1111111101110111 3
b1111111101110111 4
b1111111110111000 &
b1111111110111000 )
b1111111110111000 <
b1111111110111000 =
b10 N
1#
1$
#160000
0$
#165000
b11 1
b11101010 2
b10110 ,
b10110 8
b10110 :
b10110 ;
b11011010 /
b11000100 +
b11000100 A
b11000100 C
b11000100 D
b1001100 5
b1011010010000 7
b1001100 6
b11100000 >
b1100010000000000 @
b11100000 ?
b1111111110110100 %
b1111111110110100 (
b1111111110110100 3
b1111111110110100 4
b1111111100100000 &
b1111111100100000 )
b1111111100100000 <
b1111111100100000 =
b11 N
1#
1$
#170000
0$
#175000
b100 1
b111000100 2
b10 ,
b10 8
b10 :
b10 ;
b110011 /
b110001 +
b110001 A
b110001 C
b110001 D
b11011 5
b1011011001 7
b11011 6
b1110001 >
b11000111100001 @
b1110001 ?
b11011 %
b11011 (
b11011 3
b11011 4
b1110001 &
b1110001 )
b1110001 <
b1110001 =
b0 N
1#
1$
#180000
0$
#185000
b101 1
b111110111 2
b10010 /
b10000 +
b10000 A
b10000 C
b10000 D
b1000001 >
b1000010000001 @
b1000001 ?
b1000001 &
b1000001 )
b1000001 <
b1000001 =
b1 N
1#
1$
#190000
0$
#195000
b110 1
b1000001001 2
b1000100 ,
b1000100 8
b1000100 :
b1000100 ;
b11111011 /
b10110111 +
b10110111 A
b10110111 C
b10110111 D
b10000100 5
b100010000010000 7
b10000100 6
b11011001 >
b1011011111110001 @
b11011001 ?
b1111111101111100 %
b1111111101111100 (
b1111111101111100 3
b1111111101111100 4
b11011001 &
b11011001 )
b11011001 <
b11011001 =
b10 N
1#
1$
#200000
0$
#205000
b111 1
b1100000100 2
b1000010 ,
b1000010 8
b1000010 :
b1000010 ;
b1110110111 /
b1101110101 +
b1101110101 A
b1101110101 C
b1101110101 D
b10000010 5
b100001000000100 7
b10000010 6
b111011100 >
b110111010100010000 @
b111011100 ?
b10000010 %
b10000010 (
b10000010 3
b10000010 4
b1111111000100100 &
b1111111000100100 )
b1111111000100100 <
b1111111000100100 =
b11 N
1#
1$
#210000
0$
#215000
b11010111011 "
b11010111011 0
1*
1!
b100 N
0#
1$
#220000
0$
#225000
b0 1
b0 2
1$
#230000
0$
#235000
0*
0!
b10011111 ,
b10011111 8
b10011111 :
b10011111 ;
b11111011 /
b1011100 +
b1011100 A
b1011100 C
b1011100 D
b11001010 5
b1001111101100100 7
b11001010 6
b10011010 >
b101110010100100 @
b10011010 ?
b1111111100110110 %
b1111111100110110 (
b1111111100110110 3
b1111111100110110 4
b1111111101100110 &
b1111111101100110 )
b1111111101100110 <
b1111111101100110 =
1#
b0 N
b101 M
b100 L
b10 K
1$
#240000
0$
#245000
b1 1
b11111011 2
b1101 ,
b1101 8
b1101 :
b1101 ;
b1111 /
b10 +
b10 A
b10 C
b10 D
b111010 5
b110100100100 7
b111010 6
b10111 >
b1000010001 @
b10111 ?
b111010 %
b111010 (
b111010 3
b111010 4
b1111111111101001 &
b1111111111101001 )
b1111111111101001 <
b1111111111101001 =
b1 N
1#
1$
#250000
0$
#255000
b10 1
b100001010 2
b1011011 ,
b1011011 8
b1011011 :
b1011011 ;
b1111001 /
b11110 +
b11110 A
b11110 C
b11110 D
b10011001 5
b101101101110001 7
b10011001 6
b1011000 >
b1111001000000 @
b1011000 ?
b1111111101100111 %
b1111111101100111 (
b1111111101100111 3
b1111111101100111 4
b1111111110101000 &
b1111111110101000 )
b1111111110101000 <
b1111111110101000 =
b10 N
1#
1$
#260000
0$
#265000
b11 1
b110000011 2
b10 ,
b10 8
b10 :
b10 ;
b101110100 /
b101110010 +
b101110010 A
b101110010 C
b101110010 D
b11010 5
b1010100100 7
b11010 6
b100110100 >
b10111001010010000 @
b100110100 ?
b11010 %
b11010 (
b11010 3
b11010 4
b1111111011001100 &
b1111111011001100 )
b1111111011001100 <
b1111111011001100 =
b11 N
1#
1$
#270000
0$
#275000
b100 1
b1011110111 2
b11111 ,
b11111 8
b11111 :
b11111 ;
b100001 /
b10 +
b10 A
b10 C
b10 D
b1011010 5
b1111110100100 7
b1011010 6
b11000 >
b1001000000 @
b11000 ?
b1011010 %
b1011010 (
b1011010 3
b1011010 4
b11000 &
b11000 )
b11000 <
b11000 =
b0 N
1#
1$
#280000
0$
#285000
b101 1
b1100011000 2
b101110 ,
b101110 8
b101110 :
b101110 ;
b111111 /
b10001 +
b10001 A
b10001 C
b10001 D
b1101101 5
b10111001101001 7
b1101101 6
b1000011 >
b1000110001001 @
b1000011 ?
b1101101 %
b1101101 (
b1101101 3
b1101101 4
b1000011 &
b1000011 )
b1000011 <
b1000011 =
b1 N
1#
1$
#290000
0$
#295000
b110 1
b1101010111 2
b10100 ,
b10100 8
b10100 :
b10100 ;
b10110 /
b10 +
b10 A
b10 C
b10 D
b1001001 5
b1010011010001 7
b1001001 6
b11010 >
b1010100100 @
b11010 ?
b1111111110110111 %
b1111111110110111 (
b1111111110110111 3
b1111111110110111 4
b11010 &
b11010 )
b11010 <
b11010 =
b10 N
1#
1$
#300000
0$
#305000
b111 1
b1101101101 2
b1000000 ,
b1000000 8
b1000000 :
b1000000 ;
b1100011001 /
b1011011001 +
b1011011001 A
b1011011001 C
b1011011001 D
b10000000 5
b100000000000000 7
b10000000 6
b110110000 >
b101101100100000000 @
b110110000 ?
b10000000 %
b10000000 (
b10000000 3
b10000000 4
b1111111001010000 &
b1111111001010000 )
b1111111001010000 <
b1111111001010000 =
b11 N
1#
1$
#310000
0$
#315000
b11010000110 "
b11010000110 0
1*
1!
b100 N
0#
1$
#320000
0$
#325000
b0 1
b0 2
1$
