qmult.v
module qmult #(
	//Parameterized values
	parameter Q = 16,
	parameter N = 32
	)
	(
	 input	signed	[N-1:0]	i_multiplicand,
	 input	signed	[N-1:0]	i_multiplier,
	 output	signed	[N-1:0]	o_result,
	 output	reg	ovr
	 );
	 
	wire signed [2*N-1:0]	r_result;//Nhan 2 so cos gia tri N bit thi can 1 thanh ghi co do rong la N+N = 2N 
	reg signed [N-1:0]	r_RetVal;

	wire signed [N-1:0] temp_multiplicand, temp_meltiplier;
	reg signed  [N-1:0] temp_RetVal;
	reg is_signed;

	//--------------------------------------------------------------------------------
	assign o_result = r_RetVal;	//	Chi lay ket qua co cung so bit theo cau truc cua fixed point

	//---------------------------------------------------------------------------------
	//always @(i_multiplicand, i_multiplier) begin//Thuc hien nhan bat cu khi nao input thay doi
	// Thuc hien kiem tra bit dau
	assign temp_multiplicand = i_multiplicand[N-1] ? -i_multiplicand : i_multiplicand;
	assign temp_meltiplier = i_multiplier[N-1] ? -i_multiplier : i_multiplier;
	assign r_result = temp_meltiplier * temp_multiplicand;
	//end

	always @(r_result) begin//Bat cu khi nao ket qua thay doi thi thuc hien
		is_signed = i_multiplicand[N-1] ^ i_multiplier[N-1];	// Kiem tra bit co dau
		temp_RetVal[N-2:0] = r_result[N-2+Q:Q];			// Bo N/2 bit dau vaf N/2 bit cuoi
		temp_RetVal[N-1] = 0;					// so khong cos dau
		r_RetVal = is_signed ? -temp_RetVal : temp_RetVal;
		
		ovr = |r_result[2*N-2:N-1+Q];// Neu N/2 bit dau >0 thi phep toan tran
	end

endmodule

cmult.v

//---------------------------------------------------------------------------------------------------------------
//---------------------------------------------------------------------------------------------------------------
//---------------------------------------------------------------------------------------------------------------
module cmult # (
    parameter Q = 8, 
    parameter N = 16
)
(
    input clk,
    input rst,
    input signed  [N-1:0] ar, ai,
    input signed  [N-1:0] br, bi,
    output signed [N-1:0] pr, pi
);

reg signed [N-1:0] ar_d, ar_dd, ar_ddd, ar_dddd;
reg signed [N-1:0] ai_d, ai_dd, ai_ddd, ai_dddd;
reg signed [N-1:0] br_d, br_dd, br_ddd, bi_d, bi_dd, bi_ddd;
reg signed [N-1:0] addcommon ;
reg signed [N-1:0] addr, addi ;
reg signed [N-1:0] mult0, multr, multi;
reg signed  [N-1:0] common, commonr1, commonr2;
reg signed  [N-1:0] pr_int, pi_int;

wire signed [N-1:0] tmp_mult0, tmp_multr, tmp_multi;
wire ovr_mult0, ovr_multr, ovr_multi; // Overflow flags for multipliers
/*
always @(ar,ai,br,bi)  begin //      Thuc hien nhan bat cu khi     nao input thay doi
                  // Thuc hien kiem tra bit dau
	temp_ar = ar[N-1] ? -ar : ar;
	temp_ai = ai[N-1] ? -ai : ai;
	temp_br = br[N-1] ? -br : br;
	temp_bi = bi[N-1] ? -bi : bi;
end
always @(r_result) begin
 	//Bat cu khi nao ket qua thay doi thi thuc hien
	is_signed = i_multiplicand[N-1] ^ i_multiplier[N-1];    // Kiem tra bit co dau
	temp_RetVal[N-2:0] = r_result[N-2+Q:Q];                 // Bo N/2 bit dau vaf N/2 bit cuoi
	temp_RetVal[N-1] = 0;                                   // so khong cos dau
	r_RetVal = is_signed ? -temp_RetVal : temp_RetVal;

	ovr = |r_result[2*N-2:N-1+Q];           // Neu N/2 bit dau >0 thi phep toan tran
end
*/
// Pipeline stage 1: Input register
always @(posedge clk) begin
  	if(rst) begin
		ar_d <= 0;
		ai_d <= 0;	
		br_d <= 0;
		bi_d <= 0;
	end
	else begin
    		ar_d <= ar;
    		ar_dd <= ar_d;
    		ai_d <= ai;
    		ai_dd <= ai_d;
    		br_d <= br;
    		br_dd <= br_d;
    		br_ddd <= br_dd;
    		bi_d <= bi;
    		bi_dd <= bi_d;
    		bi_ddd <= bi_dd;
	end
end

// Pipeline stage 2: Common factor multiplication
always @(posedge clk) begin
	addcommon <= ar_d - ai_d;
	mult0 <= tmp_mult0;//addcommon * bi_dd;
	common <= mult0;
end

qmult #(.Q(Q), .N(N)) qmult_common (
    .i_multiplicand(addcommon), 
    .i_multiplier(bi_dd), 
    .o_result(tmp_mult0),
    .ovr(ovr_mult0)
);
/*
always @(posedge clk) begin
    common <= mult0;
end
*/
// Pipeline stage 3: Real product calculation
always @(posedge clk) begin
	ar_ddd <= ar_dd;
	ar_dddd <= ar_ddd;
	addr <= br_ddd - bi_ddd;
	multr <=  tmp_multr;//addr * ar_dddd;
	commonr1 <= common;
	pr_int <= multr + commonr1;
end

/*
always @(posedge clk) begin
	addr <= br_ddd - bi_ddd;
	
end
*/
qmult #(.Q(Q), .N(N)) qmult_real (
    .i_multiplicand(addr), 
    .i_multiplier(ar_dddd), 
    .o_result(tmp_multr),
    .ovr(ovr_multr)
);
/*
always @(posedge clk) begin
    commonr1 <= common;
    pr_int <= multr + commonr1; 
end
*/
// Pipeline stage 4: Imaginary product calculation

always @(posedge clk)
begin
	ai_ddd <= ai_dd;
	ai_dddd <= ai_ddd;
	addi <= br_ddd + bi_ddd;
	multi <= tmp_multi;//addi * ai_dddd;
	commonr2 <= common;
	pi_int <= multi + commonr2;
end
/*
always @(posedge clk) begin
	addi <= br_ddd + bi_ddd;
end
*/
qmult #(.Q(Q), .N(N)) qmult_imag (
    .i_multiplicand(addi), 
    .i_multiplier(ai_dddd), 
    .o_result(tmp_multi),
    .ovr(ovr_multi)
);
/*
always @(posedge clk) begin
    commonr2 <= common;
    pi_int <= multi + commonr2; 
end
*/
// Output assignment
/*
assign pr[N-2:0] = pr_int[N-2+Q:Q];
assign pr[N-1] = 0;
assign pi[N-2:0] = pi_int[N-2+Q:Q];
assign pi[N-1] = 0;
*/
assign pr = pr_int;
assign pi = pi_int;

endmodule // cmult

c_mac.v
/*
* Module: c_mac
* Chức năng: Tích lũy Nhân Phức (Complex Multiplier Accumulator)
* Sửa lỗi: Đồng bộ hóa pipeline 5 chu kỳ của khối nhân (cmult)
* Phương pháp: Sử dụng pipeline valid signal để điều khiển tích lũy.
*/

//`include "cmult.sv" // Giả định cmult có độ trễ 5 chu kỳ
module c_mac #(
    parameter Q = 8,  // Độ rộng bit phần thập phân (Fixed-point)
    parameter N = 16 // Tổng độ rộng bit
)
(
    input clk,
    input rst,
    input mac_clear,
    input mac_en, // Tín hiệu báo hiệu dữ liệu (in_ar, in_ai, in_br, in_bi) là hợp lệ
    input signed [N-1:0] in_ar, in_ai,
    input signed [N-1:0] in_br, in_bi,

    output reg signed [32-1:0] mac_r_out, mac_i_out,
    output reg mac_result_valid // Báo hiệu kết quả tích lũy mac_r_out/mac_i_out là hợp lệ
);
    wire mac_rs_valid;
    //wire product_valid_out;
    localparam LATENCY = 6; // Độ trễ của module cmult.sv
    // Dây nối để nhận kết quả từ khối nhân
    // Kích thước đầu ra của phép nhân là 2*N - 1, nhưng ta sẽ để N bit để tích lũy
    // Giả sử module cmult.sv đã xử lý việc giới hạn bit (truncation/saturation)
    wire signed [N-1:0] product_r, product_i;
    
    reg [1:0] mac_counter;
    // --- 1. Thanh ghi và Dây nối cho Tích lũy (Accumulator) ---
    // Thanh ghi tích lũy phải có độ rộng bit lớn hơn để tránh tràn số (overflow).
    // Phép nhân 16x16 cho ra 32 bit. Nếu tích lũy 8 lần, ta cần ít nhất 35 bit.
    // Dùng 2*N bit để đơn giản hóa logic (32 bit)
    localparam ACC_WIDTH = 2*N; 
    reg signed [ACC_WIDTH-1:0] mac_r_reg, mac_i_reg,mac_r_tmp,mac_i_tmp;
    
    // --- 2. Bộ tạo Tín hiệu Hợp lệ (Valid Signal Generator) ---
    // Tín hiệu valid cần được trễ 5 chu kỳ để đồng bộ với product_r/product_i
    reg [LATENCY-1:0] data_valid_pipe;
    wire product_valid = data_valid_pipe[LATENCY-1]; // Bit cuối cùng là valid output
   /// Internal Counter
    always @(posedge clk or posedge rst) begin
	if(rst) mac_counter <= 2'b0;
	else if(mac_clear) mac_counter <= 2'b0;
	else if (mac_counter == 2'b11) mac_counter <= 2'b0;
	else if (product_valid) mac_counter <= mac_counter+1'b1;
    end

    always @(posedge clk or posedge rst) begin
        if (rst) begin
            data_valid_pipe <= {LATENCY{1'b0}}; // Reset tất cả về 0
        end else begin
	    mac_result_valid <= mac_rs_valid;
            // Trễ tín hiệu valid (5-stage pipeline)
            data_valid_pipe <= {data_valid_pipe[LATENCY-2:0], mac_en};
        end
    end
    
    // --- 3. Khối Nhân Phức (cmult instantiation) ---
    // Giả định cmult.sv là khối nhân 5-stage pipeline
    cmult #( .Q(Q), .N(N) )
    cmult_inst (
        .clk(clk),
        .rst(rst),
        .ar(in_ar),
        .ai(in_ai),
        .br(in_br),
        .bi(in_bi),
        .pr(product_r),
        .pi(product_i)
    );

    // --- 4. Logic cho Thanh ghi Tích lũy (Accumulation Logic) ---
    always @(posedge clk or posedge rst) begin
        if (rst) begin
            mac_r_reg <= {ACC_WIDTH{1'b0}};
            mac_i_reg <= {ACC_WIDTH{1'b0}};
        end else if (mac_clear) begin
            // Xóa ngay lập tức (Xóa đầu ra của phép tích lũy, không phải đầu ra của cmult)
            mac_r_reg <= {ACC_WIDTH{1'b0}};
            mac_i_reg <= {ACC_WIDTH{1'b0}};
	    mac_r_tmp <= mac_r_reg;
	    mac_i_tmp <= mac_i_reg;
        end else if (product_valid) begin
            // CHỈ THỰC HIỆN TÍCH LŨY KHI KẾT QUẢ NHÂN HỢP LỆ (product_valid = 1)
            // Lưu ý: Phép cộng này xảy ra trong chu kỳ thứ 6 sau khi dữ liệu vào được nạp
            mac_r_reg <= mac_r_reg + {{ACC_WIDTH-N{product_r[N-1]}}, product_r};
            mac_i_reg <= mac_i_reg + {{ACC_WIDTH-N{product_i[N-1]}}, product_i};
            // Ký hiệu mở rộng (Sign Extension) được sử dụng để cộng product_r/i (N bit) với
            // mac_r_reg/i (ACC_WIDTH bit)
        end
    end
    
    // --- 5. Gán Đầu ra (Output Assignment) ---
    // Giới hạn (Trừncate) kết quả tích lũy 2*N bit về N bit đầu ra. 
    // Trong một thiết kế thực tế, cần dùng logic làm tròn/giới hạn (Rounding/Saturation)
    always @(posedge clk or posedge rst) begin
	if(rst) begin
		mac_r_out <= 0;
		mac_i_out <= 0;
	end else if(mac_rs_valid) begin
    		mac_r_out <=  mac_r_reg + {{ACC_WIDTH-N{product_r[N-1]}}, product_r}; 
		mac_i_out <=  mac_i_reg + {{ACC_WIDTH-N{product_i[N-1]}}, product_i};
	end
    end
  //  assign mac_i_out = (mac_rs_valid)? mac_i_reg[N-1:0]: 0;
   // assign product_valid_out = product_valid;
    assign mac_rs_valid = (product_valid && mac_counter == 3)? 1:0;
endmodule

trace_caculator.v
/*
* Module: trace_calculator
* Chức năng: Tính tử số trace(YH * G) cho khối x_metric_calculator.
* Y có kích thước 4x2, G có kích thước 4x2. YH là 2x4. Tích YH*G là 2x2.
*/
module trace_calculator #(
    parameter N = 16,
    parameter Q = 8,
    parameter ACC_WIDTH = 32
)
(
    input clk,
    input rst,
    input start_calc, // Bắt đầu tính

    // Giao diện đọc Y_RAM (giả định có sẵn bên ngoài)
    output reg [2:0] y_rd_addr,
    input signed [N-1:0] y_rd_data_r,
    input signed [N-1:0] y_rd_data_i,

    // Giao diện đọc G_RAM (giả định có sẵn bên ngoài)
    output reg [2:0] g_rd_addr,
    input signed [N-1:0] g_rd_data_r,
    input signed [N-1:0] g_rd_data_i,

    // Đầu ra
    output reg done_calc,
    output reg signed [ACC_WIDTH-1:0] trace_result_r,
    output reg signed [ACC_WIDTH-1:0] trace_result_i
);

// --- 1. FSM, MAC và Counters ---
localparam S_IDLE            = 4'd0;
localparam S_CALC_P00_CLEAR  = 4'd1;
localparam S_CALC_P00_FEED   = 4'd2;
localparam S_CALC_P00_WAIT   = 4'd3;
localparam S_CALC_P11_CLEAR  = 4'd4;
localparam S_CALC_P11_FEED   = 4'd5;
localparam S_CALC_P11_WAIT   = 4'd6;
localparam S_ADD_TRACE       = 4'd7;
localparam S_DONE            = 4'd8;

reg [3:0] state, next_state;
reg [1:0] k_counter; // Đếm 0-3 cho dot product

// Tín hiệu điều khiển MAC
reg mac_en, mac_clear;
wire mac_result_valid;
wire signed [ACC_WIDTH-1:0] mac_result_r, mac_result_i;

// Thanh ghi lưu kết quả trung gian P[0][0]
reg signed [ACC_WIDTH-1:0] p00_reg_r, p00_reg_i;

// --- 2. Logic tính YH on-the-fly ---
// YH[i][k] = Y[k][i]*
wire signed [N-1:0] yh_data_r;
wire signed [N-1:0] yh_data_i;

assign yh_data_r = y_rd_data_r;
assign yh_data_i = -y_rd_data_i; // Liên hợp phức

// --- 3. Thể hiện c_mac ---
c_mac #( .N(N), .Q(Q) )
mac_engine (
    .clk(clk), .rst(rst),
    .mac_clear(mac_clear),
    .mac_en(mac_en),
    .in_ar(yh_data_r), .in_ai(yh_data_i), // YH
    .in_br(g_rd_data_r), .in_bi(g_rd_data_i), // G
    .mac_r_out(mac_result_r),
    .mac_i_out(mac_result_i),
    .mac_result_valid(mac_result_valid)
);

// --- 4. Logic FSM và Counters ---
always @(posedge clk or rst) begin
    if (rst) begin
        state <= S_IDLE;
        k_counter <= 0;
    end else begin
        state <= next_state;
        // Cập nhật k_counter
        if (next_state == S_IDLE || next_state == S_CALC_P00_CLEAR || next_state == S_CALC_P11_CLEAR) begin
            k_counter <= 0;
        end else if (state == S_CALC_P00_FEED || state == S_CALC_P11_FEED) begin
            k_counter <= k_counter + 1;
        end
    end
end

always @(*) begin
    next_state = state;
    mac_clear = 1'b0;
    mac_en = 1'b0;
    done_calc = 1'b0;
    y_rd_addr = 0;
    g_rd_addr = 0;

    case (state)
        S_IDLE: if (start_calc) next_state = S_CALC_P00_CLEAR;
        
        // --- Tính P[0][0] = dot(YH[0,:], G[:,0]) ---
        S_CALC_P00_CLEAR: begin
            mac_clear = 1'b1;
            next_state = S_CALC_P00_FEED;
        end
        S_CALC_P00_FEED: begin
            mac_en = 1'b1;
            y_rd_addr = {k_counter, 1'b0}; // Đọc Y[k][0] để tính YH[0][k]
            g_rd_addr = {k_counter, 1'b0}; // Đọc G[k][0]
            if (k_counter == 2'b11) next_state = S_CALC_P00_WAIT;
        end
        S_CALC_P00_WAIT: if (mac_result_valid) next_state = S_CALC_P11_CLEAR;
        
        // --- Tính P[1][1] = dot(YH[1,:], G[:,1]) ---
        S_CALC_P11_CLEAR: begin
            mac_clear = 1'b1;
            next_state = S_CALC_P11_FEED;
        end
        S_CALC_P11_FEED: begin
            mac_en = 1'b1;
            y_rd_addr = {k_counter, 1'b1}; // Đọc Y[k][1] để tính YH[1][k]
            g_rd_addr = {k_counter, 1'b1}; // Đọc G[k][1]
            if (k_counter == 2'b11) next_state = S_CALC_P11_WAIT;
        end
        S_CALC_P11_WAIT: if (mac_result_valid) next_state = S_ADD_TRACE;

        // --- Cộng và Hoàn tất ---
        S_ADD_TRACE: next_state = S_DONE;
        S_DONE: begin
            done_calc = 1'b1;
            next_state = S_IDLE;

        end
        default: next_state = S_IDLE;
    endcase
end

// --- 5. Logic lưu trữ và tính toán cuối cùng ---
always @(posedge clk or rst) begin
    if (rst) begin
        p00_reg_r <= 0;
        p00_reg_i <= 0;
        trace_result_r <= 0;
        trace_result_i <= 0;
    end else begin
        // Lưu P[0][0]
        if (state == S_CALC_P00_WAIT && mac_result_valid) begin
            p00_reg_r <= mac_result_r;
            p00_reg_i <= mac_result_i;
        end
        
        // Tính trace = P[0][0] + P[1][1]
        if (state == S_ADD_TRACE) begin
            trace_result_r <= p00_reg_r + mac_result_r; // mac_result lúc này là của P[1][1]
            trace_result_i <= p00_reg_i + mac_result_i;
        end
    end
end

endmodule

tb_trace_caculator.sv
`timescale 1ns/1ps

module tb_trace_calculator;

    // --- Các tham số ---
    parameter Q = 8;
    parameter N = 16;
    parameter ACC_WIDTH = 32;
    parameter CLK_PERIOD = 10;

    // Kích thước ma trận Y và G là 4x2 = 8 phần tử
    parameter MATRIX_ELEMENTS = 8;


    // --- Tín hiệu Testbench ---
    reg clk;
    reg rst;
    reg start_calc;

    // Giao tiếp với DUT
    wire [2:0] y_rd_addr;
    wire signed [N-1:0] y_rd_data_r; // Sửa thành wire
    wire signed [N-1:0] y_rd_data_i; // Sửa thành wire

    wire [2:0] g_rd_addr;
    wire signed [N-1:0] g_rd_data_r; // Sửa thành wire
    wire signed [N-1:0] g_rd_data_i; // Sửa thành wire

    wire done_calc;
    wire signed [ACC_WIDTH-1:0] trace_result_r;
    wire signed [ACC_WIDTH-1:0] trace_result_i;

    // --- Bộ nhớ để lưu trữ dữ liệu Y và G ---
    reg signed [N-1:0] y_stim_r [0:MATRIX_ELEMENTS-1];
    reg signed [N-1:0] y_stim_i [0:MATRIX_ELEMENTS-1];
    reg signed [N-1:0] g_stim_r [0:MATRIX_ELEMENTS-1];
    reg signed [N-1:0] g_stim_i [0:MATRIX_ELEMENTS-1];

    // --- Khởi tạo DUT (Device Under Test) ---
    trace_calculator #(
        .N(N),
        .ACC_WIDTH(ACC_WIDTH)
    ) dut (
        .clk(clk),
        .rst(rst),
        .start_calc(start_calc),
        .y_rd_addr(y_rd_addr),
        .y_rd_data_r(y_rd_data_r),
        .y_rd_data_i(y_rd_data_i),
        .g_rd_addr(g_rd_addr),
        .g_rd_data_r(g_rd_data_r),
        .g_rd_data_i(g_rd_data_i),
        .done_calc(done_calc),
        .trace_result_r(trace_result_r),
        .trace_result_i(trace_result_i)
    );

    // --- Logic Testbench ---

    // Tạo clock
    always #(CLK_PERIOD/2) clk = ~clk;

    // **ĐÃ SỬA LỖI: Mô phỏng RAM tổ hợp (không có độ trễ đọc)**
    assign y_rd_data_r = y_stim_r[y_rd_addr];
    assign y_rd_data_i = y_stim_i[y_rd_addr];
    assign g_rd_data_r = g_stim_r[g_rd_addr];
    assign g_rd_data_i = g_stim_i[g_rd_addr];

    // Luồng test chính
    initial begin
        $dumpfile("tb_trace_calculator.vcd");
        $dumpvars(0, tb_trace_calculator);

        initialize_signals();
        reset_dut();

        // Nạp dữ liệu vào các bộ nhớ của testbench
        generate_y_matrix();
        generate_g_matrix(); // Tạo ma trận G mẫu

        // Chạy 1 test case
        run_one_trace_calculation();
        
        $display("\n--- Test Sequence Finished ---");
        $finish;
    end

    // --- Các Task Cho Testbench ---
    task initialize_signals;
    begin
	clk = 0;
        start_calc = 0;
    end
    endtask

    task reset_dut;
    begin
        rst = 1;
        #(2 * CLK_PERIOD);
        rst = 0;
        #(2 * CLK_PERIOD);
    end
    endtask

    
    task generate_y_matrix;
    begin
        $display("Generating a sample Y matrix...");
        // Y[0,0] = 1+j1
        y_stim_r[0] = 1 << Q; y_stim_i[0] = 1 << Q;
        // G[0,1] = 2+j2
        y_stim_r[1] = 2 << Q; y_stim_i[1] = 2 << Q;
        // G[1,0] = 3+j3
        y_stim_r[2] = 3 << Q; y_stim_i[2] = 3 << Q;
        // G[1,1] = 1+j1
        y_stim_r[3] = 1 << Q; y_stim_i[3] = 1 << Q;
        // G[2,0] = 1+j1
        y_stim_r[4] = 1 << Q; y_stim_i[4] = 1 << Q;
        // G[2,1] = 1+j2
        y_stim_r[5] = 1 << Q; y_stim_i[5] = 2 << Q;
        // G[3,0] = 1+j3
        y_stim_r[6] = 1 << Q; y_stim_i[6] = 3 << Q;
        // G[3,1] = 1+j4
        y_stim_r[7] = 1 << Q; y_stim_i[7] = 4 << Q;
    end
    endtask
    // Task tự tạo ma trận G mẫu
    task generate_g_matrix;
    begin
        $display("Generating a sample G matrix...");
        // G[0,0] = 1+j1
        g_stim_r[0] = 1 << Q; g_stim_i[0] = 1 << Q;
        // G[0,1] = 2+j2
        g_stim_r[1] = 2 << Q; g_stim_i[1] = 2 << Q;
        // G[1,0] = 3+j3
        g_stim_r[2] = 2 << Q; g_stim_i[2] = 3 << Q;
        // G[1,1] = 4+j4
        g_stim_r[3] = 2 << Q; g_stim_i[3] = 4 << Q;
        // G[2,0] = 5+j1
        g_stim_r[4] = 5 << Q; g_stim_i[4] = 1 << Q;
        // G[2,1] = 6+j2
        g_stim_r[5] = 6 << Q; g_stim_i[5] = 2 << Q;
        // G[3,0] = 7+j3
        g_stim_r[6] = 7 << Q; g_stim_i[6] = 3 << Q;
        // G[3,1] = 8+j4
        g_stim_r[7] = 8 << Q; g_stim_i[7] = 4 << Q;
    end
    endtask

    // Task thực thi một phép tính trace
    task run_one_trace_calculation;
    begin
        $display("\n--- Running Trace Calculation Test ---");
        
        // Kích hoạt DUT
        @(posedge clk);
        start_calc = 1;
        @(posedge clk);
        start_calc = 0;

        // Chờ DUT tính xong
        $display("Waiting for DUT to complete...");
        wait(done_calc);

        // In kết quả
        $display(">>> DUT Trace Result (Real) = %h (%f)", trace_result_r, $signed(trace_result_r)/(2.0**Q));
        $display(">>> DUT Trace Result (Imag) = %h (%f)", trace_result_i, $signed(trace_result_i)/(2.0**Q));
        
        @(posedge clk);
    end
    endtask

endmodule

tb_trace_calculator.vcd
$date
	Mon Oct  6 21:52:52 2025
$end
$version
	Icarus Verilog
$end
$timescale
	1ps
$end
$scope module tb_trace_calculator $end
$var wire 16 ! g_rd_data_i [15:0] $end
$var wire 16 " g_rd_data_r [15:0] $end
$var wire 16 # y_rd_data_i [15:0] $end
$var wire 16 $ y_rd_data_r [15:0] $end
$var wire 3 % y_rd_addr [2:0] $end
$var wire 32 & trace_result_r [31:0] $end
$var wire 32 ' trace_result_i [31:0] $end
$var wire 3 ( g_rd_addr [2:0] $end
$var wire 1 ) done_calc $end
$var reg 1 * clk $end
$var reg 1 + rst $end
$var reg 1 , start_calc $end
$scope module dut $end
$var wire 1 * clk $end
$var wire 16 - g_rd_data_i [15:0] $end
$var wire 16 . g_rd_data_r [15:0] $end
$var wire 1 + rst $end
$var wire 1 , start_calc $end
$var wire 16 / y_rd_data_i [15:0] $end
$var wire 16 0 y_rd_data_r [15:0] $end
$var wire 16 1 yh_data_r [15:0] $end
$var wire 16 2 yh_data_i [15:0] $end
$var wire 1 3 mac_result_valid $end
$var wire 32 4 mac_result_r [31:0] $end
$var wire 32 5 mac_result_i [31:0] $end
$var reg 1 ) done_calc $end
$var reg 3 6 g_rd_addr [2:0] $end
$var reg 2 7 k_counter [1:0] $end
$var reg 1 8 mac_clear $end
$var reg 1 9 mac_en $end
$var reg 4 : next_state [3:0] $end
$var reg 32 ; p00_reg_i [31:0] $end
$var reg 32 < p00_reg_r [31:0] $end
$var reg 4 = state [3:0] $end
$var reg 32 > trace_result_i [31:0] $end
$var reg 32 ? trace_result_r [31:0] $end
$var reg 3 @ y_rd_addr [2:0] $end
$scope module mac_engine $end
$var wire 1 * clk $end
$var wire 16 A in_ai [15:0] $end
$var wire 16 B in_ar [15:0] $end
$var wire 16 C in_bi [15:0] $end
$var wire 16 D in_br [15:0] $end
$var wire 1 8 mac_clear $end
$var wire 1 9 mac_en $end
$var wire 1 + rst $end
$var wire 1 E product_valid $end
$var wire 16 F product_r [15:0] $end
$var wire 16 G product_i [15:0] $end
$var wire 1 H mac_rs_valid $end
$var reg 6 I data_valid_pipe [5:0] $end
$var reg 2 J mac_counter [1:0] $end
$var reg 32 K mac_i_out [31:0] $end
$var reg 32 L mac_i_reg [31:0] $end
$var reg 32 M mac_i_tmp [31:0] $end
$var reg 32 N mac_r_out [31:0] $end
$var reg 32 O mac_r_reg [31:0] $end
$var reg 32 P mac_r_tmp [31:0] $end
$var reg 1 3 mac_result_valid $end
$scope module cmult_inst $end
$var wire 16 Q ai [15:0] $end
$var wire 16 R ar [15:0] $end
$var wire 16 S bi [15:0] $end
$var wire 16 T br [15:0] $end
$var wire 1 * clk $end
$var wire 16 U pi [15:0] $end
$var wire 16 V pr [15:0] $end
$var wire 1 + rst $end
$var wire 16 W tmp_multr [15:0] $end
$var wire 16 X tmp_multi [15:0] $end
$var wire 16 Y tmp_mult0 [15:0] $end
$var wire 1 Z ovr_multr $end
$var wire 1 [ ovr_multi $end
$var wire 1 \ ovr_mult0 $end
$var reg 16 ] addcommon [15:0] $end
$var reg 16 ^ addi [15:0] $end
$var reg 16 _ addr [15:0] $end
$var reg 16 ` ai_d [15:0] $end
$var reg 16 a ai_dd [15:0] $end
$var reg 16 b ai_ddd [15:0] $end
$var reg 16 c ai_dddd [15:0] $end
$var reg 16 d ar_d [15:0] $end
$var reg 16 e ar_dd [15:0] $end
$var reg 16 f ar_ddd [15:0] $end
$var reg 16 g ar_dddd [15:0] $end
$var reg 16 h bi_d [15:0] $end
$var reg 16 i bi_dd [15:0] $end
$var reg 16 j bi_ddd [15:0] $end
$var reg 16 k br_d [15:0] $end
$var reg 16 l br_dd [15:0] $end
$var reg 16 m br_ddd [15:0] $end
$var reg 16 n common [15:0] $end
$var reg 16 o commonr1 [15:0] $end
$var reg 16 p commonr2 [15:0] $end
$var reg 16 q mult0 [15:0] $end
$var reg 16 r multi [15:0] $end
$var reg 16 s multr [15:0] $end
$var reg 16 t pi_int [15:0] $end
$var reg 16 u pr_int [15:0] $end
$scope module qmult_common $end
$var wire 16 v i_multiplicand [15:0] $end
$var wire 16 w i_multiplier [15:0] $end
$var wire 16 x o_result [15:0] $end
$var wire 16 y temp_multiplicand [15:0] $end
$var wire 16 z temp_meltiplier [15:0] $end
$var wire 32 { r_result [31:0] $end
$var reg 1 | is_signed $end
$var reg 1 \ ovr $end
$var reg 16 } r_RetVal [15:0] $end
$var reg 16 ~ temp_RetVal [15:0] $end
$upscope $end
$scope module qmult_imag $end
$var wire 16 !" i_multiplicand [15:0] $end
$var wire 16 "" i_multiplier [15:0] $end
$var wire 16 #" o_result [15:0] $end
$var wire 16 $" temp_multiplicand [15:0] $end
$var wire 16 %" temp_meltiplier [15:0] $end
$var wire 32 &" r_result [31:0] $end
$var reg 1 '" is_signed $end
$var reg 1 [ ovr $end
$var reg 16 (" r_RetVal [15:0] $end
$var reg 16 )" temp_RetVal [15:0] $end
$upscope $end
$scope module qmult_real $end
$var wire 16 *" i_multiplicand [15:0] $end
$var wire 16 +" i_multiplier [15:0] $end
$var wire 16 ," o_result [15:0] $end
$var wire 16 -" temp_multiplicand [15:0] $end
$var wire 16 ." temp_meltiplier [15:0] $end
$var wire 32 /" r_result [31:0] $end
$var reg 1 0" is_signed $end
$var reg 1 Z ovr $end
$var reg 16 1" r_RetVal [15:0] $end
$var reg 16 2" temp_RetVal [15:0] $end
$upscope $end
$upscope $end
$upscope $end
$upscope $end
$scope task generate_g_matrix $end
$upscope $end
$scope task generate_y_matrix $end
$upscope $end
$scope task initialize_signals $end
$upscope $end
$scope task reset_dut $end
$upscope $end
$scope task run_one_trace_calculation $end
$upscope $end
$upscope $end
$enddefinitions $end
#0
$dumpvars
bx 2"
bx 1"
x0"
bx /"
bx ."
bx -"
bx ,"
bx +"
bx *"
bx )"
bx ("
x'"
bx &"
bx %"
bx $"
bx #"
bx ""
bx !"
bx ~
bx }
x|
bx {
bx z
bx y
bx x
bx w
bx v
bx u
bx t
bx s
bx r
bx q
bx p
bx o
bx n
bx m
bx l
bx k
bx j
bx i
bx h
bx g
bx f
bx e
bx d
bx c
bx b
bx a
bx `
bx _
bx ^
bx ]
x\
x[
xZ
bx Y
bx X
bx W
bx V
bx U
bx T
bx S
bx R
bx Q
bx P
b0 O
b0 N
bx M
b0 L
b0 K
b0 J
b0 I
0H
bx G
bx F
0E
bx D
bx C
bx B
bx A
b0 @
b0 ?
b0 >
b0 =
b0 <
b0 ;
b0 :
09
08
b0 7
b0 6
b0 5
b0 4
x3
bx 2
bx 1
bx 0
bx /
bx .
bx -
0,
1+
0*
0)
b0 (
b0 '
b0 &
b0 %
bx $
bx #
bx "
bx !
$end
#5000
b0 h
b0 k
b0 `
b0 d
1*
#10000
0*
#15000
b0 y
b0 ]
b0 v
1*
#20000
0*
0+
#25000
0\
b0 Y
b0 x
b0 }
b0 ~
0|
b0 {
b0 z
b0 i
b0 w
bx h
b0 l
bx k
b0 a
bx `
b0 e
bx d
03
1*
#30000
0*
#35000
x\
bx Y
bx x
bx }
b0xxxxxxxxxxxxxxx ~
x|
bx y
bx {
bx z
b0 b
b0 f
b0 q
bx ]
bx v
b0 j
bx i
bx w
b0 m
bx l
bx a
bx e
1*
#40000
0*
b100000000 !
b100000000 -
b100000000 C
b100000000 S
b100000000 "
b100000000 .
b100000000 D
b100000000 T
b1111111100000000 2
b1111111100000000 A
b1111111100000000 Q
b100000000 #
b100000000 /
b100000000 1
b100000000 B
b100000000 R
b100000000 $
b100000000 0
#45000
0Z
b0 W
b0 ,"
b0 1"
b0 2"
00"
0[
b0 X
b0 #"
b0 ("
b0 )"
0'"
b0 /"
b0 -"
b0 ."
b0 &"
b0 $"
b0 %"
bx j
b100000000 h
bx m
b100000000 k
b1111111100000000 `
b100000000 d
b0 n
bx q
b0 _
b0 *"
b0 g
b0 +"
bx f
b0 ^
b0 !"
b0 c
b0 ""
bx b
b1 :
1,
1*
#50000
0*
#55000
0\
b1000000000 Y
b1000000000 x
b1000000000 }
b1000000000 ~
0|
x[
bx X
bx #"
bx ("
b0xxxxxxxxxxxxxxx )"
x'"
xZ
bx W
bx ,"
bx 1"
b0xxxxxxxxxxxxxxx 2"
x0"
b100000000000000000 {
bx $"
bx &"
bx %"
bx -"
bx /"
bx ."
b1000000000 y
b100000000 z
18
b0 p
b0 r
bx ^
bx !"
bx c
bx ""
b0 o
b0 s
bx _
bx *"
bx g
bx +"
bx n
b1000000000 ]
b1000000000 v
b100000000 i
b100000000 w
b100000000 l
b1111111100000000 a
b100000000 e
b1 =
b10 :
0,
1*
#60000
0*
#65000
19
08
b100000000 j
b100000000 m
b1000000000 q
b0 F
b0 V
b0 u
bx o
bx s
b100000000 f
b0 G
b0 U
b0 t
bx p
bx r
b1111111100000000 b
b0 M
b0 P
b10 =
1*
#70000
0*
